examples/__init__.py
examples/docx_example.py
examples/pptx_example.py
py_redact/__init__.py
py_redact/docx_redactor.py
py_redact/pptx_redactor.py
py_redact_datumbrain-0.0.3.dist-info/LICENSE
py_redact_datumbrain-0.0.3.dist-info/METADATA
py_redact_datumbrain-0.0.3.dist-info/WHEEL
py_redact_datumbrain-0.0.3.dist-info/top_level.txt
py_redact_datumbrain-0.0.3.dist-info/RECORD
