Metadata-Version: 2.1
Name: py-redact-datumbrain
Version: 0.0.3
Summary: A python package to redact documents by regexes.
Home-page: https://github.com/pypa/sampleproject
Author: Fahad Siddiqui
Author-email: fsdqui@gmail.com
License: UNKNOWN
Platform: UNKNOWN
Classifier: Programming Language :: Python :: 3
Classifier: License :: OSI Approved :: MIT License
Classifier: Operating System :: OS Independent
Requires-Python: >=3.7
Requires-Dist: python-docx (==0.8.10)
Requires-Dist: python-pptx (==0.6.18)
